[
    {
        "id": 0,
        "name": "AntJam",
        "qr": "AntJam",
        "AliveCharacter": {
            "descriptionKey": "AntJamAlive",
            "effectiveness": 1,
            "morale": 2
        },
        "DeadCharacter": {
            "descriptionKey": "AntJamDead",
            "morale": -3
        }
    },
    {
        "id": 1,
        "name": "WalSim",
        "qr": "WalSim",
        "AliveCharacter": {
            "descriptionKey": "WalSimAlive",
            "effectiveness": 1,
            "morale": 1
        },
        "DeadCharacter": {
            "descriptionKey": "WalSimDead",
            "morale": -2
        }
    },
    {
        "id": 2,
        "name": "ChrWat",
        "qr": "ChrWat",
        "AliveCharacter": {
            "descriptionKey": "ChrWatAlive",
            "morale": 1
        },
        "DeadCharacter": {
            "descriptionKey": "ChrWatDead",
            "morale": -1
        }
    },
    {
        "id": 3,
        "name": "AndLad",
        "qr": "AndLad",
        "AliveCharacter": {
            "descriptionKey": "AndLadAlive",
            "effectiveness": 2,
            "morale": 2
        },
        "DeadCharacter": {
            "descriptionKey": "AndLadDead",
            "morale": -3
        }
    },
    {
        "id": 4,
        "name": "MatRow",
        "qr": "MatRow",
        "AliveCharacter": {
            "descriptionKey": "MatRowAlive",
            "effectiveness": 1,
            "morale": 1
        },
        "DeadCharacter": {
            "descriptionKey": "MatRowDead",
            "morale": -2
        }
    },
    {
        "id": 5,
        "name": "GorPhi",
        "qr": "GorPhi",
        "AliveCharacter": {
            "descriptionKey": "GorPhiAlive",
            "effectiveness": 1,
            "morale": 1
        },
        "DeadCharacter": {
            "descriptionKey": "GorPhiDead",
            "morale": -2
        }
    },
    {
        "id": 6,
        "name": "JerWes",
        "qr": "JerWes",
        "AliveCharacter": {
            "descriptionKey": "JerWesAlive",
            "effectiveness": 1,
            "morale": 1
        },
        "DeadCharacter": {
            "descriptionKey": "JerWesDead",
            "morale": -2
        }
    },
    {
        "id": 7,
        "name": "WilCoo",
        "qr": "WilCoo",
        "AliveCharacter": {
            "descriptionKey": "WilCooAlive",
            "effectiveness": 2,
            "morale": 2,
            "trigger": 280
        },
        "DeadCharacter": {
            "descriptionKey": "WilCooDead",
            "morale": -3,
            "trigger": 281
        }
    },
    {
        "id": 8,
        "name": "EwaTan",
        "qr": "EwaTan",
        "AliveCharacter": {
            "descriptionKey": "EwaTanAlive",
            "alternativeDescriptionTrigger": 89,
            "alternativeDescription": "EwaTanAliveAlternative",
            "effectiveness": 1
        },
        "DeadCharacter": {
            "descriptionKey": "EwaTanDead",
            "alternativeDescriptionTrigger": 89,
            "alternativeDescription": "EwaTanDeadAlternative",
            "morale": -1
        }
    },
    {
        "id": 9,
        "name": "HenSta",
        "qr": "HenSta",
        "AliveCharacter": {
            "descriptionKey": "HenStaAlive",
            "alternativeDescriptionTrigger": 89,
            "alternativeDescription": "HenStaAliveAlternative",
            "effectiveness": 1,
            "morale": 1
        },
        "DeadCharacter": {
            "descriptionKey": "HenStaDead",
            "alternativeDescriptionTrigger": 89,
            "alternativeDescription": "HenStaDeadAlternative",
            "morale": -1
        }
    },
    {
        "id": 10,
        "name": "GeoWid",
        "qr": "GeoWid",
        "AliveCharacter": {
            "descriptionKey": "GeoWidAlive",
            "effectiveness": 1
        },
        "DeadCharacter": {
            "descriptionKey": "GeoWidDead",
            "morale": -2
        }
    },
    {
        "id": 11,
        "name": "BenWin",
        "qr": "BenWin",
        "AliveCharacter": {
            "descriptionKey": "BenWinAlive",
            "alternativeDescriptionTrigger": 89,
            "alternativeDescription": "BenWinAliveAlternative",
            "effectiveness": 1,
            "morale": 1
        },
        "DeadCharacter": {
            "descriptionKey": "BenWinDead",
            "alternativeDescriptionTrigger": 89,
            "alternativeDescription": "BenWinDeadAlternative",
            "morale": -2
        }
    },
    {
        "id": 12,
        "name": "AlbCum",
        "qr": "AlbCum",
        "AliveCharacter": {
            "descriptionKey": "AlbCumAlive",
            "effectiveness": 1,
            "morale": 1
        },
        "DeadCharacter": {
            "descriptionKey": "AlbCumDead",
            "morale": -2
        }
    },
    {
        "id": 13,
        "name": "GerLaf",
        "qr": "GerLaf",
        "AliveCharacter": {
            "descriptionKey": "GerLafAlive",
            "effectiveness": 1,
            "morale": 2
        },
        "DeadCharacter": {
            "descriptionKey": "GerLafDead",
            "effectiveness": -1,
            "morale": -2,
            "trigger": 442
        }
    },
    {
        "id": 14,
        "name": "PieTul",
        "qr": "PieTul",
        "AliveCharacter": {
            "descriptionKey": "PieTulAlive",
            "effectiveness": 1
        },
        "DeadCharacter": {
            "descriptionKey": "PieTulDead",
            "effectiveness": -1
        }
    },
    {
        "id": 15,
        "name": "GuyLed",
        "qr": "PieTul",
        "AliveCharacter": {
            "descriptionKey": "PieTulAlive",
            "effectiveness": 1,
            "morale": 2,
            "trigger": 449
        },
        "DeadCharacter": {
            "descriptionKey": "PieTulDead",
            "effectiveness": -1,
            "morale": -1
        }
    },
    {
        "id": 16,
        "name": "LudGri",
        "qr": "LudGri",
        "AliveCharacter": {
            "descriptionKey": "LudGriAlive",
            "alternativeDescriptionTrigger": 449,
            "alternativeDescription": "LudGriAliveAlternative",
            "effectiveness": 1
        },
        "DeadCharacter": {
            "descriptionKey": "LudGriDead",
            "alternativeDescriptionTrigger": 449,
            "alternativeDescription": "LudGriDeadAlternative",
            "morale": -1,
            "effectiveness": -1
        }
    },
    {
        "id": 17,
        "name": "FabPie",
        "qr": "FabPie",
        "AliveCharacter": {
            "descriptionKey": "FabPieAlive",
            "alternativeDescriptionTrigger": 517,
            "alternativeDescription": "FabPieAliveAlternative",
            "effectiveness": 1,
            "morale": -1,
            "trigger": 591
        },
        "DeadCharacter": {
            "descriptionKey": "FabPieDead",
            "alternativeDescriptionTrigger": 517,
            "alternativeDescription": "FabPieDeadAlternative",
            "morale": -1,
            "effectiveness": -2
        }
    },
    {
        "id": 18,
        "name": "WilMcc",
        "qr": "WilMcc",
        "AliveCharacter": {
            "descriptionKey": "WilMccAlive",
            "effectiveness": 2,
            "morale": 1,
            "trigger": 597
        },
        "DeadCharacter": {
            "descriptionKey": "WilMccDead",
            "effectiveness": -2,
            "morale": 1
        }
    },
    {
        "id": 19,
        "name": "GeoTow",
        "qr": "GeoTow",
        "AliveCharacter": {
            "descriptionKey": "GeoTowAlive",
            "effectiveness": 1,
            "morale": 1,
            "trigger": 603
        },
        "DeadCharacter": {
            "descriptionKey": "GeoTowDead",
            "effectiveness": 1,
            "morale": 1
        }
    },
    {
        "id": 20,
        "name": "JamLic",
        "qr": "JamLic",
        "AliveCharacter": {
            "descriptionKey": "JamLicAlive",
            "effectiveness": 1,
            "morale": 1
        },
        "DeadCharacter": {
            "descriptionKey": "JamLicDead",
            "effectiveness": -1,
            "morale": -1
        }
    },
    {
        "id": 21,
        "name": "TimLaw",
        "qr": "TimLaw",
        "AliveCharacter": {
            "descriptionKey": "TimLawAlive",
            "effectiveness": 2,
            "morale": 3,
            "trigger": 615
        },
        "DeadCharacter": {
            "descriptionKey": "TimLawDead",
            "effectiveness": -2,
            "morale": -2
        }
    },
    {
        "id": 22,
        "name": "ChaWin",
        "qr": "ChaWin",
        "AliveCharacter": {
            "descriptionKey": "ChaWinAlive",
            "effectiveness": 1,
            "trigger": 621
        },
        "DeadCharacter": {
            "descriptionKey": "ChaWinDead",
            "effectiveness": -2
        }
    },
    {
        "id": 23,
        "name": "AdrDeL",
        "qr": "AdrDeL",
        "AliveCharacter": {
            "descriptionKey": "AdrDeLAlive",
            "alternativeDescriptionTrigger": 722,
            "alternativeDescription": "AdrDeLAliveAlternative",
            "effectiveness": 1,
            "morale": 1
        },
        "DeadCharacter": {
            "descriptionKey": "AdrDeLDead",
            "morale": -1,
            "effectiveness": -1
        }
    },
    {
        "id": 24,
        "name": "BerDes",
        "qr": "BerDes",
        "AliveCharacter": {
            "descriptionKey": "BerDesAlive",
            "effectiveness": 1,
            "morale": 1
        },
        "DeadCharacter": {
            "descriptionKey": "BerDesDead",
            "effectiveness": -1,
            "morale": -1
        }
    },
    {
        "id": 25,
        "name": "ChrPol",
        "qr": "ChrPol",
        "AliveCharacter": {
            "descriptionKey": "ChrPolAlive",
            "effectiveness": 3,
            "morale": 1
        },
        "DeadCharacter": {
            "descriptionKey": "ChrPolDead",
            "effectiveness": -1,
            "morale": -2
        }
    },
    {
        "id": 26,
        "name": "BlaPom",
        "qr": "BlaPom",
        "AliveCharacter": {
            "descriptionKey": "BlaPomAlive",
            "alternativeDescriptionTrigger": 722,
            "alternativeDescription": "BlaPomAliveAlternative",
            "effectiveness": 1,
            "morale": 1
        },
        "DeadCharacter": {
            "descriptionKey": "BlaPomDead",
            "effectiveness": -1,
            "morale": -1
        }
    },
    {
        "id": 26,
        "name": "AndRoi",
        "qr": "AndRoi",
        "AliveCharacter": {
            "descriptionKey": "AndRoiAlive",
            "effectiveness": 2,
            "morale": 1
        },
        "DeadCharacter": {
            "descriptionKey": "AndRoiDead",
            "effectiveness": -1,
            "morale": -1
        }
    },
    {
        "id": 27,
        "name": "CJFlyn",
        "qr": "CJFlyn",
        "AliveCharacter": {
            "descriptionKey": "CJFlynAlive",
            "effectiveness": 2,
            "morale": 3
        },
        "DeadCharacter": {
            "descriptionKey": "CJFlynDead",
            "effectiveness": -3,
            "morale": -1
        }
    }
]